whey_pth/__init__.py
whey_pth/py.typed
whey_pth-0.0.6.dist-info/LICENSE
whey_pth-0.0.6.dist-info/METADATA
whey_pth-0.0.6.dist-info/WHEEL
whey_pth-0.0.6.dist-info/entry_points.txt
whey_pth-0.0.6.dist-info/top_level.txt
whey_pth-0.0.6.dist-info/RECORD
