Metadata-Version: 2.1
Name: whey-pth
Version: 0.0.6
Summary: Extension to whey to support .pth files.
Home-page: https://github.com/repo-helper/whey-pth
Author: Dominic Davis-Foster
Author-email: Dominic Davis-Foster <dominic@davis-foster.co.uk>
License: Copyright (c) 2021 Dominic Davis-Foster
Project-URL: Homepage, https://github.com/repo-helper/whey-pth
Project-URL: Issue Tracker, https://github.com/repo-helper/whey-pth/issues
Project-URL: Source Code, https://github.com/repo-helper/whey-pth
Project-URL: Documentation, https://whey-pth.readthedocs.io/en/latest
Keywords: build,distribution,packaging,wheel,whey
Platform: Windows
Platform: macOS
Platform: Linux
Classifier: Development Status :: 3 - Alpha
Classifier: Environment :: Console
Classifier: Intended Audience :: Developers
Classifier: License :: OSI Approved :: MIT License
Classifier: Operating System :: OS Independent
Classifier: Programming Language :: Python
Classifier: Programming Language :: Python :: 3 :: Only
Classifier: Programming Language :: Python :: 3.6
Classifier: Programming Language :: Python :: 3.7
Classifier: Programming Language :: Python :: 3.8
Classifier: Programming Language :: Python :: 3.9
Classifier: Programming Language :: Python :: 3.10
Classifier: Programming Language :: Python :: 3.11
Classifier: Programming Language :: Python :: 3.12
Classifier: Programming Language :: Python :: Implementation :: CPython
Classifier: Programming Language :: Python :: Implementation :: PyPy
Classifier: Topic :: Software Development :: Build Tools
Classifier: Topic :: Software Development :: Libraries :: Python Modules
Classifier: Topic :: System :: Archiving :: Packaging
Classifier: Typing :: Typed
Requires-Python: >=3.6.1
License-File: LICENSE
Requires-Dist: dom-toml >=0.4.0
Requires-Dist: whey >=0.0.25
